<?xml version="1.0" encoding="utf-8" ?>
<!-- Copyright 2022 Camptocamp SA
     License AGPL-3.0 or later (http://www.gnu.org/licenses/agpl). -->
<odoo>

    <record id="shopfloor_menu_demo_reception" model="shopfloor.menu">
        <field name="name">Reception</field>
        <field name="sequence">45</field>
        <field name="profile_id" ref="shopfloor.profile_demo_1" />
        <field name="scenario_id" ref="shopfloor_reception.scenario_reception" />
        <field
            name="picking_type_ids"
            eval="[(4, ref('shopfloor_reception.picking_type_reception_demo'))]"
        />
    </record>


</odoo>
